a_pandas_ex_mindex_aggregate/LICENSE
a_pandas_ex_mindex_aggregate/README.MD
a_pandas_ex_mindex_aggregate/__init__.py
a_pandas_ex_mindex_aggregate/requirements.txt
a_pandas_ex_mindex_aggregate/thirdparty.json
a_pandas_ex_mindex_aggregate-0.10.dist-info/LICENSE.rst
a_pandas_ex_mindex_aggregate-0.10.dist-info/METADATA
a_pandas_ex_mindex_aggregate-0.10.dist-info/WHEEL
a_pandas_ex_mindex_aggregate-0.10.dist-info/top_level.txt
a_pandas_ex_mindex_aggregate-0.10.dist-info/RECORD
