Metadata-Version: 2.1
Name: a-pandas-ex-mindex-aggregate
Version: 0.10
Summary: Aggregates multiple columns of a DataFrame
Home-page: https://github.com/hansalemaos/a_pandas_ex_mindex_aggregate
Author: Johannes Fischer
Author-email: <aulasparticularesdealemaosp@gmail.com>
License: MIT
Keywords: pandas,Aggregate,DataFrame
Classifier: Development Status :: 4 - Beta
Classifier: Programming Language :: Python :: 3 :: Only
Classifier: Programming Language :: Python :: 3.9
Classifier: Topic :: Scientific/Engineering :: Visualization
Classifier: Topic :: Software Development :: Libraries :: Python Modules
Classifier: Topic :: Text Editors :: Text Processing
Classifier: Topic :: Text Processing :: General
Classifier: Topic :: Text Processing :: Indexing
Classifier: Topic :: Text Processing :: Filters
Classifier: Topic :: Utilities
License-File: LICENSE.rst
Requires-Dist: numpy
Requires-Dist: pandas
